WalletPay/AsyncWalletPayAPI.py
WalletPay/Exception.py
WalletPay/Order.py
WalletPay/WalletPayAPI.py
WalletPay/WebhookManager.py
WalletPay/__init__.py
WalletPay/types/Exception.py
WalletPay/types/Order.py
WalletPay/types/OrderPreview.py
WalletPay/types/OrderReconciliationItem.py
WalletPay/types/WebhookData.py
WalletPay/types/__init__.py
WalletPay-1.3.1.dist-info/LICENSE
WalletPay-1.3.1.dist-info/METADATA
WalletPay-1.3.1.dist-info/WHEEL
WalletPay-1.3.1.dist-info/top_level.txt
WalletPay-1.3.1.dist-info/RECORD
