Metadata-Version: 2.1
Name: WalletPay
Version: 1.3.1
Summary: A Python client for the API pay.wallet.tg.
Home-page: https://github.com/xdownedx/WalletPay
Author: Max Palehin
Author-email: maksim.wsem@gmail.com
Classifier: Programming Language :: Python :: 3
Classifier: License :: OSI Approved :: MIT License
Classifier: Operating System :: OS Independent
License-File: LICENSE
